Workbook

Sheet Pricing
A1: IGU Pricing — coaching ladder + add-ons
A2: Coach pay = Price − IGU keeps − Ops. Prices in 5s; IGU keep eases by level. Edit blue cells.
A4: Service | B4: Level | C4: Client price | D4: IGU keeps | E4: Ops | F4: Coach pay | G4: Coach % | H4: Level mix
A5: Team Plan | B5: All | C5: 10 | D5: 2 | E5: 2 | F5: =C5-D5-E5 -> 6 | G5: =F5/C5 -> 0.6 | H5: 1
A6: 1:1 Online | B6: Junior | C6: 30 | D6: 10 | E6: 3 | F6: =C6-D6-E6 -> 17 | G6: =F6/C6 -> 0.56666667 | H6: 0.5
B7: Senior | C7: 35 | D7: 8 | E7: 3 | F7: =C7-D7-E7 -> 24 | G7: =F7/C7 -> 0.68571429 | H7: 0.35
B8: Lead | C8: 40 | D8: 7 | E8: 3 | F8: =C8-D8-E8 -> 30 | G8: =F8/C8 -> 0.75 | H8: 0.15
A9: Hybrid | B9: Junior | C9: 95 | D9: 20 | E9: 5 | F9: =C9-D9-E9 -> 70 | G9: =F9/C9 -> 0.73684211 | H9: 0.5
B10: Senior | C10: 110 | D10: 17 | E10: 5 | F10: =C10-D10-E10 -> 88 | G10: =F10/C10 -> 0.8 | H10: 0.35
B11: Lead | C11: 125 | D11: 15 | E11: 5 | F11: =C11-D11-E11 -> 105 | G11: =F11/C11 -> 0.84 | H11: 0.15
A12: In-Person | B12: Junior | C12: 145 | D12: 30 | E12: 8 | F12: =C12-D12-E12 -> 107 | G12: =F12/C12 -> 0.73793103 | H12: 0.5
B13: Senior | C13: 175 | D13: 26 | E13: 8 | F13: =C13-D13-E13 -> 141 | G13: =F13/C13 -> 0.80571429 | H13: 0.35
B14: Lead | C14: 215 | D14: 24 | E14: 8 | F14: =C14-D14-E14 -> 183 | G14: =F14/C14 -> 0.85116279 | H14: 0.15
A15: Add-ons (FUTURE — referral partners, MOH-licensed). Attach % = 0 so they're excluded from counts until launched.
A16: Add-on | C16: Price | D16: IGU keeps | E16: Ops | F16: Pro pay | G16: Pro % | H16: Attach %
A17: Nutrition (monthly) | C17: 30 | D17: 7 | E17: 2 | F17: =C17-D17-E17 -> 21 | G17: =F17/C17 -> 0.7 | H17: 0
A18: Physio remote (monthly) | C18: 45 | D18: 8 | E18: 4 | F18: =C18-D18-E18 -> 33 | G18: =F18/C18 -> 0.73333333 | H18: 0
A20: Add-on uplift per active client (attach-weighted)
A21: + ARPU | C21: =C17*H17+C18*H18 -> 0
A22: + Pro payout | C22: =F17*H17+F18*H18 -> 0
A23: + Ops | C23: =E17*H17+E18*H18 -> 0
A24: + IGU keep | C24: =D17*H17+D18*H18 -> 0
A26: Per-service blended (by level mix)
A27: Service | B27: Service mix | C27: Blended price | D27: Coach pay | E27: Ops | F27: IGU keeps
A28: Team Plan | B28: 0.35 | C28: =C5 -> 10 | D28: =F5 -> 6 | E28: =E5 -> 2 | F28: =D5 -> 2
A29: 1:1 Online | B29: 0.35 | C29: =C6*H6+C7*H7+C8*H8 -> 33.25 | D29: =F6*H6+F7*H7+F8*H8 -> 21.4 | E29: =E6*H6+E7*H7+E8*H8 -> 3 | F29: =D6*H6+D7*H7+D8*H8 -> 8.85
A30: Hybrid | B30: 0.2 | C30: =C9*H9+C10*H10+C11*H11 -> 104.75 | D30: =F9*H9+F10*H10+F11*H11 -> 81.55 | E30: =E9*H9+E10*H10+E11*H11 -> 5 | F30: =D9*H9+D10*H10+D11*H11 -> 18.2
A31: In-Person | B31: 0.1 | C31: =C12*H12+C13*H13+C14*H14 -> 166 | D31: =F12*H12+F13*H13+F14*H14 -> 130.3 | E31: =E12*H12+E13*H13+E14*H14 -> 8 | F31: =D12*H12+D13*H13+D14*H14 -> 27.7
A32: Mix check | B32: =SUM(B28:B31) -> 1
A34: Blended per client (coaching only; add-ons excluded at attach 0) — drives the projection
A35: Blended ARPU (KWD/client) | C35: =SUMPRODUCT(C28:C31,B28:B31)+C21 -> 52.6875
A36: Blended coach + pro payout | C36: =SUMPRODUCT(D28:D31,B28:B31)+C22 -> 38.93
A37: Blended ops | C37: =SUMPRODUCT(E28:E31,B28:B31)+C23 -> 3.55
A38: Blended IGU net per client | C38: =SUMPRODUCT(F28:F31,B28:B31)+C24 -> 10.2075

Sheet Assumptions
A1: Assumptions
A3: Starting capital (KWD) | B3: 0
A4: Monthly churn rate | B4: 0.1
A6: Operating fixed costs (KWD/month)
A7: Software & infrastructure | B7: 60
A8: Marketing & misc | B8: 50
A9: Accountant / bookkeeper (outsourced) | B9: 100
A10: Operating fixed total | B10: =B7+B8+B9 -> 210

Sheet Projection
A1: 18-Month Projection from 0 clients (incl add-ons)
A2: Blue = inputs (new clients, founder draw, dev). Prices/payouts/add-ons come from the Pricing sheet.
A4: Month | B4: New clients | C4: Churned | D4: Active | E4: Total MRR | F4: Coach+Pro | G4: Ops | H4: IGU gross | I4: Op. fixed | J4: Founder draw | K4: Dev / contractor | L4: Net | M4: Cumul. cash
A5: Start | D5: 0
A6: Jul-26 | B6: 20 | C6: =D5*Assumptions!$B$4 -> 0 | D6: =D5*(1-Assumptions!$B$4)+B6 -> 20 | E6: =D6*Pricing!$C$35 -> 1053.75 | F6: =D6*Pricing!$C$36 -> 778.6 | G6: =D6*Pricing!$C$37 -> 71 | H6: =E6-F6-G6 -> 204.15 | I6: =Assumptions!$B$10 -> 210 | J6: 0 | K6: 0 | L6: =H6-I6-J6-K6 -> -5.85 | M6: =Assumptions!$B$3+L6 -> -5.85
A7: Aug-26 | B7: 18 | C7: =D6*Assumptions!$B$4 -> 2 | D7: =D6*(1-Assumptions!$B$4)+B7 -> 36 | E7: =D7*Pricing!$C$35 -> 1896.75 | F7: =D7*Pricing!$C$36 -> 1401.48 | G7: =D7*Pricing!$C$37 -> 127.8 | H7: =E7-F7-G7 -> 367.47 | I7: =Assumptions!$B$10 -> 210 | J7: 0 | K7: 0 | L7: =H7-I7-J7-K7 -> 157.47 | M7: =M6+L7 -> 151.62
A8: Sep-26 | B8: 20 | C8: =D7*Assumptions!$B$4 -> 3.6 | D8: =D7*(1-Assumptions!$B$4)+B8 -> 52.4 | E8: =D8*Pricing!$C$35 -> 2760.825 | F8: =D8*Pricing!$C$36 -> 2039.932 | G8: =D8*Pricing!$C$37 -> 186.02 | H8: =E8-F8-G8 -> 534.873 | I8: =Assumptions!$B$10 -> 210 | J8: 0 | K8: 0 | L8: =H8-I8-J8-K8 -> 324.873 | M8: =M7+L8 -> 476.493
A9: Oct-26 | B9: 22 | C9: =D8*Assumptions!$B$4 -> 5.24 | D9: =D8*(1-Assumptions!$B$4)+B9 -> 69.16 | E9: =D9*Pricing!$C$35 -> 3643.8675 | F9: =D9*Pricing!$C$36 -> 2692.3988 | G9: =D9*Pricing!$C$37 -> 245.518 | H9: =E9-F9-G9 -> 705.9507 | I9: =Assumptions!$B$10 -> 210 | J9: 0 | K9: 0 | L9: =H9-I9-J9-K9 -> 495.9507 | M9: =M8+L9 -> 972.4437
A10: Nov-26 | B10: 24 | C10: =D9*Assumptions!$B$4 -> 6.916 | D10: =D9*(1-Assumptions!$B$4)+B10 -> 86.244 | E10: =D10*Pricing!$C$35 -> 4543.9807 | F10: =D10*Pricing!$C$36 -> 3357.4789 | G10: =D10*Pricing!$C$37 -> 306.1662 | H10: =E10-F10-G10 -> 880.33563 | I10: =Assumptions!$B$10 -> 210 | J10: 0 | K10: 0 | L10: =H10-I10-J10-K10 -> 670.33563 | M10: =M9+L10 -> 1642.7793
A11: Dec-26 | B11: 25 | C11: =D10*Assumptions!$B$4 -> 8.6244 | D11: =D10*(1-Assumptions!$B$4)+B11 -> 102.6196 | E11: =D11*Pricing!$C$35 -> 5406.7702 | F11: =D11*Pricing!$C$36 -> 3994.981 | G11: =D11*Pricing!$C$37 -> 364.29958 | H11: =E11-F11-G11 -> 1047.4896 | I11: =Assumptions!$B$10 -> 210 | J11: 0 | K11: 0 | L11: =H11-I11-J11-K11 -> 837.48957 | M11: =M10+L11 -> 2480.2689
A12: Jan-27 | B12: 26 | C12: =D11*Assumptions!$B$4 -> 10.26196 | D12: =D11*(1-Assumptions!$B$4)+B12 -> 118.35764 | E12: =D12*Pricing!$C$35 -> 6235.9682 | F12: =D12*Pricing!$C$36 -> 4607.6629 | G12: =D12*Pricing!$C$37 -> 420.16962 | H12: =E12-F12-G12 -> 1208.1356 | I12: =Assumptions!$B$10 -> 210 | J12: 0 | K12: 0 | L12: =H12-I12-J12-K12 -> 998.13561 | M12: =M11+L12 -> 3478.4045
A13: Feb-27 | B13: 27 | C13: =D12*Assumptions!$B$4 -> 11.835764 | D13: =D12*(1-Assumptions!$B$4)+B13 -> 133.52188 | E13: =D13*Pricing!$C$35 -> 7034.9338 | F13: =D13*Pricing!$C$36 -> 5198.0066 | G13: =D13*Pricing!$C$37 -> 474.00266 | H13: =E13-F13-G13 -> 1362.9245 | I13: =Assumptions!$B$10 -> 210 | J13: 0 | K13: 0 | L13: =H13-I13-J13-K13 -> 1152.9245 | M13: =M12+L13 -> 4631.3291
A14: Mar-27 | B14: 28 | C14: =D13*Assumptions!$B$4 -> 13.352188 | D14: =D13*(1-Assumptions!$B$4)+B14 -> 148.16969 | E14: =D14*Pricing!$C$35 -> 7806.6905 | F14: =D14*Pricing!$C$36 -> 5768.246 | G14: =D14*Pricing!$C$37 -> 526.00239 | H14: =E14-F14-G14 -> 1512.4421 | I14: =Assumptions!$B$10 -> 210 | J14: 0 | K14: 0 | L14: =H14-I14-J14-K14 -> 1302.4421 | M14: =M13+L14 -> 5933.7712
A15: Apr-27 | B15: 28 | C15: =D14*Assumptions!$B$4 -> 14.816969 | D15: =D14*(1-Assumptions!$B$4)+B15 -> 161.35272 | E15: =D15*Pricing!$C$35 -> 8501.2714 | F15: =D15*Pricing!$C$36 -> 6281.4614 | G15: =D15*Pricing!$C$37 -> 572.80215 | H15: =E15-F15-G15 -> 1647.0079 | I15: =Assumptions!$B$10 -> 210 | J15: 0 | K15: 0 | L15: =H15-I15-J15-K15 -> 1437.0079 | M15: =M14+L15 -> 7370.779
A16: May-27 | B16: 30 | C16: =D15*Assumptions!$B$4 -> 16.135272 | D16: =D15*(1-Assumptions!$B$4)+B16 -> 175.21745 | E16: =D16*Pricing!$C$35 -> 9231.7693 | F16: =D16*Pricing!$C$36 -> 6821.2152 | G16: =D16*Pricing!$C$37 -> 622.02194 | H16: =E16-F16-G16 -> 1788.5321 | I16: =Assumptions!$B$10 -> 210 | J16: 0 | K16: 0 | L16: =H16-I16-J16-K16 -> 1578.5321 | M16: =M15+L16 -> 8949.3111
A17: Jun-27 | B17: 30 | C17: =D16*Assumptions!$B$4 -> 17.521745 | D17: =D16*(1-Assumptions!$B$4)+B17 -> 187.6957 | E17: =D17*Pricing!$C$35 -> 9889.2173 | F17: =D17*Pricing!$C$36 -> 7306.9937 | G17: =D17*Pricing!$C$37 -> 666.31975 | H17: =E17-F17-G17 -> 1915.9039 | I17: =Assumptions!$B$10 -> 210 | J17: 0 | K17: 0 | L17: =H17-I17-J17-K17 -> 1705.9039 | M17: =M16+L17 -> 10655.215
A18: Jul-27 | B18: 30 | C18: =D17*Assumptions!$B$4 -> 18.76957 | D18: =D17*(1-Assumptions!$B$4)+B18 -> 198.92613 | E18: =D18*Pricing!$C$35 -> 10480.921 | F18: =D18*Pricing!$C$36 -> 7744.1943 | G18: =D18*Pricing!$C$37 -> 706.18777 | H18: =E18-F18-G18 -> 2030.5385 | I18: =Assumptions!$B$10 -> 210 | J18: 0 | K18: 0 | L18: =H18-I18-J18-K18 -> 1820.5385 | M18: =M17+L18 -> 12475.754
... A23: Dec-27 | B23: 30 | C23: =D22*Assumptions!$B$4 -> 23.368544 | D23: =D22*(1-Assumptions!$B$4)+B23 -> 240.31689 | E23: =D23*Pricing!$C$35 -> 12661.696 | F23: =D23*Pricing!$C$36 -> 9355.5366 | G23: =D23*Pricing!$C$37 -> 853.12497 | H23: =E23-F23-G23 -> 2453.0347 | I23: =Assumptions!$B$10 -> 210 | J23: 0 | K23: 0 | L23: =H23-I23-J23-K23 -> 2243.0347 | M23: =M22+L23 -> 22934.538
A24: 18-mo total | E24: =SUM(E6:E23) -> 137890.98 | F24: =SUM(F6:F23) -> 101885.57 | G24: =SUM(G6:G23) -> 9290.8753 | H24: =SUM(H6:H23) -> 26714.538 | I24: =SUM(I6:I23) -> 3780 | J24: =SUM(J6:J23) -> 0 | K24: =SUM(K6:K23) -> 0 | L24: =SUM(L6:L23) -> 22934.538 | M24: =M23 -> 22934.538
A26: Summary
A27: Blended ARPU incl add-ons | C27: =Pricing!$C$35 -> 52.6875
A28: Blended IGU net per client | C28: =Pricing!$C$38 -> 10.2075
A29: Active clients @ month 6 | C29: =D11 -> 102.6196
A30: Active clients @ month 12 | C30: =D17 -> 187.6957
A31: Active clients @ month 18 | C31: =D23 -> 240.31689
A32: IGU gross profit @ month 12 (monthly) | C32: =H17 -> 1915.9039
A33: Cash retained over 18 months | C33: =M23 -> 22934.538

Sheet Team & Milestones
A1: Support team — client goals per hire
A2: Coaching clients only (add-ons excluded). These are IGU's fixed costs; coaches are paid from client fees, so they're NOT here. Clients = cost ÷ IGU net (~10 KWD). Edit blue costs / reorder to set priority.
A4: Add (in priority order) | B4: Monthly cost | C4: Clients (alone) | D4: Cumulative cost | E4: Cumulative clients | F4: ≈ Month
A5: Operating base (software, accountant, marketing/tools) | B5: =Assumptions!$B$10 -> 210 | C5: =ROUNDUP(B5/Pricing!$C$38,0) -> 21 | D5: =B5 -> 210 | E5: =ROUNDUP(D5/Pricing!$C$38,0) -> 21 | F5: =IF(COUNTIF(Projection!$D$6:$D$23,"<"&E5)+1>18,">M18",INDEX(Projection!$A$6:$A$23,COUNTIF(Projection!$D$6:$D$23,"<"&E5)+1)) -> Aug-26
A6: Founder draw (initial) | B6: 150 | C6: =ROUNDUP(B6/Pricing!$C$38,0) -> 15 | D6: =D5+B6 -> 360 | E6: =ROUNDUP(D6/Pricing!$C$38,0) -> 36 | F6: =IF(COUNTIF(Projection!$D$6:$D$23,"<"&E6)+1>18,">M18",INDEX(Projection!$A$6:$A$23,COUNTIF(Projection!$D$6:$D$23,"<"&E6)+1)) -> Aug-26
A7: First partner draw (initial) | B7: 150 | C7: =ROUNDUP(B7/Pricing!$C$38,0) -> 15 | D7: =D6+B7 -> 510 | E7: =ROUNDUP(D7/Pricing!$C$38,0) -> 50 | F7: =IF(COUNTIF(Projection!$D$6:$D$23,"<"&E7)+1>18,">M18",INDEX(Projection!$A$6:$A$23,COUNTIF(Projection!$D$6:$D$23,"<"&E7)+1)) -> Sep-26
A8: Developer (contractor) | B8: 1200 | C8: =ROUNDUP(B8/Pricing!$C$38,0) -> 118 | D8: =D7+B8 -> 1710 | E8: =ROUNDUP(D8/Pricing!$C$38,0) -> 168 | F8: =IF(COUNTIF(Projection!$D$6:$D$23,"<"&E8)+1>18,">M18",INDEX(Projection!$A$6:$A$23,COUNTIF(Projection!$D$6:$D$23,"<"&E8)+1)) -> May-27
A9: Client Success & Ops (1st support hire) | B9: 500 | C9: =ROUNDUP(B9/Pricing!$C$38,0) -> 49 | D9: =D8+B9 -> 2210 | E9: =ROUNDUP(D9/Pricing!$C$38,0) -> 217 | F9: =IF(COUNTIF(Projection!$D$6:$D$23,"<"&E9)+1>18,">M18",INDEX(Projection!$A$6:$A$23,COUNTIF(Projection!$D$6:$D$23,"<"&E9)+1)) -> Sep-27
A10: Marketing contractor (social/content) | B10: 300 | C10: =ROUNDUP(B10/Pricing!$C$38,0) -> 30 | D10: =D9+B10 -> 2510 | E10: =ROUNDUP(D10/Pricing!$C$38,0) -> 246 | F10: =IF(COUNTIF(Projection!$D$6:$D$23,"<"&E10)+1>18,">M18",INDEX(Projection!$A$6:$A$23,COUNTIF(Projection!$D$6:$D$23,"<"&E10)+1)) -> >M18
A11: Finance / admin (part-time, later) | B11: 400 | C11: =ROUNDUP(B11/Pricing!$C$38,0) -> 40 | D11: =D10+B11 -> 2910 | E11: =ROUNDUP(D11/Pricing!$C$38,0) -> 286 | F11: =IF(COUNTIF(Projection!$D$6:$D$23,"<"&E11)+1>18,">M18",INDEX(Projection!$A$6:$A$23,COUNTIF(Projection!$D$6:$D$23,"<"&E11)+1)) -> >M18
A13: Clients (alone) = what that role costs on its own. Cumulative = everything up to and including it,
A14: in this priority order. ≈ Month maps the cumulative client count onto the growth ramp.
A16: IGU net per client (from Pricing) | B16: =Pricing!$C$38 -> 10.2075
A18: Founder + partner take 150 KWD/mo each now. After all hires are done they switch from
A19: fixed draws to a profit share (see plan, §6) and these draws scale with profit.
