Workbook

Sheet Assumptions
A1: IGU Finance Model — Assumptions
A2: Bootstrapped: 0 KWD starting capital. Edit blue cells to run scenarios.
A4: Key rates
A5: Starting capital (KWD) | B5: 0
A6: Monthly churn rate | B6: 0.1
A7: Coach level assumed | B7: Junior
A9: Per-tier inputs (KWD per client / month)
A10: Tier | B10: Price | C10: Coach pay | D10: Dietitian pay | E10: Ops cost | F10: Mix %
A11: Team Plan | B11: 12 | C11: 7 | D11: 0 | E11: 2 | F11: 0.35
A12: 1:1 Online | B12: 40 | C12: 20 | D12: 0 | E12: 3 | F12: 0.3
A13: 1:1 Complete | B13: 75 | C13: 20 | D13: 15 | E13: 4 | F13: 0.2
A14: Hybrid | B14: 150 | C14: 60 | D14: 15 | E14: 6 | F14: 0.1
A15: In-Person | B15: 250 | C15: 105 | D15: 15 | E15: 8 | F15: 0.05
A16: Mix check (should = 100%) | F16: =SUM(F11:F15) -> 1
A18: Blended per active client (weighted by mix)
A19: Blended price (ARPU) | B19: =SUMPRODUCT(B11:B15,F11:F15) -> 58.7
A20: Blended coach + dietitian payout | B20: =SUMPRODUCT((C11:C15+D11:D15),F11:F15) -> 28.95
A21: Blended ops cost | B21: =SUMPRODUCT(E11:E15,F11:F15) -> 3.4
A22: Blended IGU margin / client | B22: =B19-B20-B21 -> 26.35
A24: Operating fixed costs (KWD / month)
A25: Software & infrastructure | B25: 60
A26: Marketing & misc | B26: 20
A27: Operating fixed total | B27: =B25+B26 -> 80
A29: Note: founder draw & developer pay are modelled per-month on the Projection
A30: sheet (blue columns) — fund them from surplus once margin supports it.

Sheet Projection
A1: IGU Finance Model — 18-Month Projection
A2: Active clients ramp from 0. Blue cells are inputs (new clients, founder draw, dev pay). Everything else recalculates.
A4: Month | B4: New clients | C4: Churned | D4: Active | E4: MRR | F4: Coach+Diet | G4: Ops | H4: IGU gross | I4: Op. fixed | J4: Founder draw | K4: Dev / contractor | L4: Net profit | M4: Cumul. cash
A5: Start | D5: 0
A6: Jul-26 | B6: 20 | C6: =D5*Assumptions!$B$6 -> 0 | D6: =D5*(1-Assumptions!$B$6)+B6 -> 20 | E6: =D6*Assumptions!$B$19 -> 1174 | F6: =D6*Assumptions!$B$20 -> 579 | G6: =D6*Assumptions!$B$21 -> 68 | H6: =E6-F6-G6 -> 527 | I6: =Assumptions!$B$27 -> 80 | J6: 0 | K6: 0 | L6: =H6-I6-J6-K6 -> 447 | M6: =Assumptions!$B$5+L6 -> 447
A7: Aug-26 | B7: 18 | C7: =D6*Assumptions!$B$6 -> 2 | D7: =D6*(1-Assumptions!$B$6)+B7 -> 36 | E7: =D7*Assumptions!$B$19 -> 2113.2 | F7: =D7*Assumptions!$B$20 -> 1042.2 | G7: =D7*Assumptions!$B$21 -> 122.4 | H7: =E7-F7-G7 -> 948.6 | I7: =Assumptions!$B$27 -> 80 | J7: 0 | K7: 0 | L7: =H7-I7-J7-K7 -> 868.6 | M7: =M6+L7 -> 1315.6
A8: Sep-26 | B8: 20 | C8: =D7*Assumptions!$B$6 -> 3.6 | D8: =D7*(1-Assumptions!$B$6)+B8 -> 52.4 | E8: =D8*Assumptions!$B$19 -> 3075.88 | F8: =D8*Assumptions!$B$20 -> 1516.98 | G8: =D8*Assumptions!$B$21 -> 178.16 | H8: =E8-F8-G8 -> 1380.74 | I8: =Assumptions!$B$27 -> 80 | J8: 0 | K8: 0 | L8: =H8-I8-J8-K8 -> 1300.74 | M8: =M7+L8 -> 2616.34
A9: Oct-26 | B9: 22 | C9: =D8*Assumptions!$B$6 -> 5.24 | D9: =D8*(1-Assumptions!$B$6)+B9 -> 69.16 | E9: =D9*Assumptions!$B$19 -> 4059.692 | F9: =D9*Assumptions!$B$20 -> 2002.182 | G9: =D9*Assumptions!$B$21 -> 235.144 | H9: =E9-F9-G9 -> 1822.366 | I9: =Assumptions!$B$27 -> 80 | J9: 0 | K9: 0 | L9: =H9-I9-J9-K9 -> 1742.366 | M9: =M8+L9 -> 4358.706
A10: Nov-26 | B10: 24 | C10: =D9*Assumptions!$B$6 -> 6.916 | D10: =D9*(1-Assumptions!$B$6)+B10 -> 86.244 | E10: =D10*Assumptions!$B$19 -> 5062.5228 | F10: =D10*Assumptions!$B$20 -> 2496.7638 | G10: =D10*Assumptions!$B$21 -> 293.2296 | H10: =E10-F10-G10 -> 2272.5294 | I10: =Assumptions!$B$27 -> 80 | J10: 0 | K10: 0 | L10: =H10-I10-J10-K10 -> 2192.5294 | M10: =M9+L10 -> 6551.2354
A11: Dec-26 | B11: 25 | C11: =D10*Assumptions!$B$6 -> 8.6244 | D11: =D10*(1-Assumptions!$B$6)+B11 -> 102.6196 | E11: =D11*Assumptions!$B$19 -> 6023.7705 | F11: =D11*Assumptions!$B$20 -> 2970.8374 | G11: =D11*Assumptions!$B$21 -> 348.90664 | H11: =E11-F11-G11 -> 2704.0265 | I11: =Assumptions!$B$27 -> 80 | J11: 0 | K11: 0 | L11: =H11-I11-J11-K11 -> 2624.0265 | M11: =M10+L11 -> 9175.2619
A12: Jan-27 | B12: 26 | C12: =D11*Assumptions!$B$6 -> 10.26196 | D12: =D11*(1-Assumptions!$B$6)+B12 -> 118.35764 | E12: =D12*Assumptions!$B$19 -> 6947.5935 | F12: =D12*Assumptions!$B$20 -> 3426.4537 | G12: =D12*Assumptions!$B$21 -> 402.41598 | H12: =E12-F12-G12 -> 3118.7238 | I12: =Assumptions!$B$27 -> 80 | J12: 0 | K12: 0 | L12: =H12-I12-J12-K12 -> 3038.7238 | M12: =M11+L12 -> 12213.986
A13: Feb-27 | B13: 27 | C13: =D12*Assumptions!$B$6 -> 11.835764 | D13: =D12*(1-Assumptions!$B$6)+B13 -> 133.52188 | E13: =D13*Assumptions!$B$19 -> 7837.7341 | F13: =D13*Assumptions!$B$20 -> 3865.4583 | G13: =D13*Assumptions!$B$21 -> 453.97438 | H13: =E13-F13-G13 -> 3518.3014 | I13: =Assumptions!$B$27 -> 80 | J13: 0 | K13: 0 | L13: =H13-I13-J13-K13 -> 3438.3014 | M13: =M12+L13 -> 15652.287
A14: Mar-27 | B14: 28 | C14: =D13*Assumptions!$B$6 -> 13.352188 | D14: =D13*(1-Assumptions!$B$6)+B14 -> 148.16969 | E14: =D14*Assumptions!$B$19 -> 8697.5607 | F14: =D14*Assumptions!$B$20 -> 4289.5125 | G14: =D14*Assumptions!$B$21 -> 503.77694 | H14: =E14-F14-G14 -> 3904.2713 | I14: =Assumptions!$B$27 -> 80 | J14: 0 | K14: 0 | L14: =H14-I14-J14-K14 -> 3824.2713 | M14: =M13+L14 -> 19476.558
A15: Apr-27 | B15: 28 | C15: =D14*Assumptions!$B$6 -> 14.816969 | D15: =D14*(1-Assumptions!$B$6)+B15 -> 161.35272 | E15: =D15*Assumptions!$B$19 -> 9471.4046 | F15: =D15*Assumptions!$B$20 -> 4671.1612 | G15: =D15*Assumptions!$B$21 -> 548.59925 | H15: =E15-F15-G15 -> 4251.6442 | I15: =Assumptions!$B$27 -> 80 | J15: 0 | K15: 0 | L15: =H15-I15-J15-K15 -> 4171.6442 | M15: =M14+L15 -> 23648.203
A16: May-27 | B16: 30 | C16: =D15*Assumptions!$B$6 -> 16.135272 | D16: =D15*(1-Assumptions!$B$6)+B16 -> 175.21745 | E16: =D16*Assumptions!$B$19 -> 10285.264 | F16: =D16*Assumptions!$B$20 -> 5072.5451 | G16: =D16*Assumptions!$B$21 -> 595.73932 | H16: =E16-F16-G16 -> 4616.9797 | I16: =Assumptions!$B$27 -> 80 | J16: 0 | K16: 0 | L16: =H16-I16-J16-K16 -> 4536.9797 | M16: =M15+L16 -> 28185.182
A17: Jun-27 | B17: 30 | C17: =D16*Assumptions!$B$6 -> 17.521745 | D17: =D16*(1-Assumptions!$B$6)+B17 -> 187.6957 | E17: =D17*Assumptions!$B$19 -> 11017.738 | F17: =D17*Assumptions!$B$20 -> 5433.7906 | G17: =D17*Assumptions!$B$21 -> 638.16539 | H17: =E17-F17-G17 -> 4945.7818 | I17: =Assumptions!$B$27 -> 80 | J17: 0 | K17: 0 | L17: =H17-I17-J17-K17 -> 4865.7818 | M17: =M16+L17 -> 33050.964
A18: Jul-27 | B18: 30 | C18: =D17*Assumptions!$B$6 -> 18.76957 | D18: =D17*(1-Assumptions!$B$6)+B18 -> 198.92613 | E18: =D18*Assumptions!$B$19 -> 11676.964 | F18: =D18*Assumptions!$B$20 -> 5758.9115 | G18: =D18*Assumptions!$B$21 -> 676.34885 | H18: =E18-F18-G18 -> 5241.7036 | I18: =Assumptions!$B$27 -> 80 | J18: 0 | K18: 0 | L18: =H18-I18-J18-K18 -> 5161.7036 | M18: =M17+L18 -> 38212.668
... A23: Dec-27 | B23: 30 | C23: =D22*Assumptions!$B$6 -> 23.368544 | D23: =D22*(1-Assumptions!$B$6)+B23 -> 240.31689 | E23: =D23*Assumptions!$B$19 -> 14106.602 | F23: =D23*Assumptions!$B$20 -> 6957.174 | G23: =D23*Assumptions!$B$21 -> 817.07743 | H23: =E23-F23-G23 -> 6332.3501 | I23: =Assumptions!$B$27 -> 80 | J23: 0 | K23: 0 | L23: =H23-I23-J23-K23 -> 6252.3501 | M23: =M22+L23 -> 67521.849
A24: Year-1 / 18-mo | E24: =SUM(E6:E23) -> 153626.59 | F24: =SUM(F6:F23) -> 75766.434 | G24: =SUM(G6:G23) -> 8898.3031 | H24: =SUM(H6:H23) -> 68961.849 | I24: =SUM(I6:I23) -> 1440 | J24: =SUM(J6:J23) -> 0 | K24: =SUM(K6:K23) -> 0 | L24: =SUM(L6:L23) -> 67521.849 | M24: =M23 -> 67521.849
A26: Summary
A27: Blended ARPU (KWD/client) | C27: =Assumptions!$B$19 -> 58.7
A28: Blended IGU margin (KWD/client) | C28: =Assumptions!$B$22 -> 26.35
A29: Active clients @ month 6 (Dec-26) | C29: =D11 -> 102.6196
A30: Active clients @ month 12 (Jun-27) | C30: =D17 -> 187.6957
A31: Active clients @ month 18 (Dec-27) | C31: =D23 -> 240.31689
A32: IGU gross profit @ month 12 (monthly) | C32: =H17 -> 4945.7818
A33: Net cash retained over 18 months | C33: =M23 -> 67521.849
A34: Monthly surplus @ M6 (before draw/dev) | C34: =H11-I11 -> 2624.0265
A36: Bootstrap logic: coaches & dietitians are paid per client out of that client's fee, so they
A37: are a variable cost, not upfront salary. With 0 capital the business self-funds; the surplus
A38: column is the pool from which you can start paying yourself and a developer.
